build/lib/build/lib/build/lib/build/lib/build/lib/build/lib/build/lib/build/lib/build/lib/build/lib/build/lib/minchin/pelican/readers/microblog/__init__.py
build/lib/build/lib/build/lib/build/lib/build/lib/build/lib/build/lib/build/lib/build/lib/build/lib/build/lib/minchin/pelican/readers/microblog/constants.py
build/lib/build/lib/build/lib/build/lib/build/lib/build/lib/build/lib/build/lib/build/lib/build/lib/build/lib/minchin/pelican/readers/microblog/generator.py
build/lib/build/lib/build/lib/build/lib/build/lib/build/lib/build/lib/build/lib/build/lib/build/lib/build/lib/minchin/pelican/readers/microblog/initialize.py
build/lib/build/lib/build/lib/build/lib/build/lib/build/lib/build/lib/build/lib/build/lib/build/lib/minchin/pelican/readers/microblog/__init__.py
build/lib/build/lib/build/lib/build/lib/build/lib/build/lib/build/lib/build/lib/build/lib/build/lib/minchin/pelican/readers/microblog/constants.py
build/lib/build/lib/build/lib/build/lib/build/lib/build/lib/build/lib/build/lib/build/lib/build/lib/minchin/pelican/readers/microblog/generator.py
build/lib/build/lib/build/lib/build/lib/build/lib/build/lib/build/lib/build/lib/build/lib/build/lib/minchin/pelican/readers/microblog/initialize.py
build/lib/build/lib/build/lib/build/lib/build/lib/build/lib/build/lib/build/lib/build/lib/minchin/pelican/readers/microblog/__init__.py
build/lib/build/lib/build/lib/build/lib/build/lib/build/lib/build/lib/build/lib/build/lib/minchin/pelican/readers/microblog/constants.py
build/lib/build/lib/build/lib/build/lib/build/lib/build/lib/build/lib/build/lib/build/lib/minchin/pelican/readers/microblog/generator.py
build/lib/build/lib/build/lib/build/lib/build/lib/build/lib/build/lib/build/lib/build/lib/minchin/pelican/readers/microblog/initialize.py
build/lib/build/lib/build/lib/build/lib/build/lib/build/lib/build/lib/build/lib/minchin/pelican/readers/microblog/__init__.py
minchin.pelican.readers.microblog-1.3.0.dist-info/LICENSE.txt
minchin.pelican.readers.microblog-1.3.0.dist-info/METADATA
minchin.pelican.readers.microblog-1.3.0.dist-info/WHEEL
minchin.pelican.readers.microblog-1.3.0.dist-info/top_level.txt
minchin.pelican.readers.microblog-1.3.0.dist-info/RECORD
