Metadata-Version: 2.1
Name: minchin.pelican.readers.microblog
Version: 1.3.0
Summary: Microblogging for Pelican
Home-page: https://blog.minchin.ca/label/microblogging-pelican/
Author: W. Minchin
Author-email: w_minchin@hotmail.com
License: MIT License
Project-URL: Bug Tracker, https://github.com/MinchinWeb/minchin.pelican.readers.microblog/issues
Project-URL: Changelog, https://github.com/MinchinWeb/minchin.pelican.readers.microblog/blob/master/CHANGELOG.rst
Platform: any
Classifier: Development Status :: 5 - Production/Stable
Classifier: Environment :: Console
Classifier: Framework :: Pelican :: Plugins
Classifier: Programming Language :: Python :: 3
Classifier: Programming Language :: Python :: 3.9
Classifier: Programming Language :: Python :: 3.10
Classifier: Programming Language :: Python :: 3.11
Classifier: Programming Language :: Python :: 3.12
Classifier: Natural Language :: English
Classifier: Intended Audience :: Developers
Classifier: Operating System :: OS Independent
Classifier: Topic :: Software Development :: Libraries :: Python Modules
Classifier: License :: OSI Approved :: MIT License
Requires-Python: >= 3.9
License-File: LICENSE.txt
Requires-Dist: minchin.pelican.plugins.autoloader >=1.2.0
Requires-Dist: pelican
Requires-Dist: markupsafe
Requires-Dist: jinja2
Requires-Dist: markdown
Provides-Extra: all
Requires-Dist: minchin.releaser >=0.8.2 ; extra == 'all'
Requires-Dist: setuptools ; extra == 'all'
Requires-Dist: seafoam >=2.9.0 ; extra == 'all'
Requires-Dist: pelican >=2.10.3 ; extra == 'all'
Requires-Dist: markdown ; extra == 'all'
Requires-Dist: invoke ; extra == 'all'
Requires-Dist: black ; extra == 'all'
Requires-Dist: isort ; extra == 'all'
Provides-Extra: build
Requires-Dist: minchin.releaser >=0.8.2 ; extra == 'build'
Requires-Dist: setuptools ; extra == 'build'
Provides-Extra: dev
Requires-Dist: invoke ; extra == 'dev'
Requires-Dist: black ; extra == 'dev'
Requires-Dist: isort ; extra == 'dev'
Provides-Extra: docs
Provides-Extra: test
Requires-Dist: seafoam >=2.9.0 ; extra == 'test'
Requires-Dist: pelican >=2.10.3 ; extra == 'test'
Requires-Dist: markdown ; extra == 'test'
